Metadata-Version: 2.1
Name: pylibffm
Version: 0.4.0
Summary: A library wrapping libffm
Home-page: https://github.com/Sinacam/pylibffm
Author: ntumlgroup
License: MIT License
Platform: UNKNOWN
Classifier: Intended Audience :: Science/Research
Classifier: License :: OSI Approved :: MIT License
Classifier: Programming Language :: Python :: 3
Classifier: Programming Language :: Python :: 3.7
Classifier: Programming Language :: Python :: 3.8
